video_frame_extractor/__init__.py
video_frame_extractor/cli.py
video_frame_extractor/core.py
video_frame_extractor-2.0.0.dist-info/METADATA
video_frame_extractor-2.0.0.dist-info/WHEEL
video_frame_extractor-2.0.0.dist-info/entry_points.txt
video_frame_extractor-2.0.0.dist-info/top_level.txt
video_frame_extractor-2.0.0.dist-info/RECORD
